{"cameraMode":{"drawMode":0,"name":"Shaded","section":"Shading Mode"},"sceneLighting":true,"audioPlay":false,"sceneViewState":{"m_AlwaysRefresh":false,"showFog":true,"showSkybox":true,"showFlares":true,"showImageEffects":true,"showParticleSystems":true,"showVisualEffectGraphs":true,"m_FxEnabled":true},"in2DMode":false,"pivot":{"x":5.954793930053711,"y":-29.731246948242189,"z":31.581764221191408},"rotation":{"x":0.10776972025632858,"y":0.01938529685139656,"z":-0.0021017715334892275,"w":0.9939846992492676},"size":63.00914001464844,"orthographic":false}